[
  { "name": "Onur Bugdayci", "cost": 70.89 },
  { "name": "Gert Claeskens", "cost": 55.13 },
  { "name": "Igor Romy", "cost": 45.12 },
  { "name": "Bram De Plekker", "cost": 43.67 },
  { "name": "Jonathan Rasquin", "cost": 42.43 },
  { "name": "Tim Ranson", "cost": 42.19 },
  { "name": "Bernard Giorgino", "cost": 41.46 },
  { "name": "Bo Rosseel", "cost": 38.37 },
  { "name": "Tom Marroyen", "cost": 37.96 },
  { "name": "Jochem Van Hespen", "cost": 37.83 },
  { "name": "Thomas De Brauwer", "cost": 35.72 },
  { "name": "David Sverdlov", "cost": 34.44 },
  { "name": "Jelle Maes", "cost": 33.37 },
  { "name": "Joris Wijnant", "cost": 32.25 },
  { "name": "Nina Van Hoof", "cost": 27.10 },
  { "name": "Timo Versonnen", "cost": 25.33 },
  { "name": "Nicolas Legrand", "cost": 25.14 },
  { "name": "Heleen de Meue", "cost": 25.07 },
  { "name": "Yannick Manfroy", "cost": 25.06 },
  { "name": "Joachim D'hondt", "cost": 23.28 },
  { "name": "Jelle Muijzelaar", "cost": 20.97 },
  { "name": "Bert Maes", "cost": 19.87 },
  { "name": "Remco Verbruggen", "cost": 19.39 },
  { "name": "Wim De Blende", "cost": 19.26 },
  { "name": "Jos Van Loock", "cost": 16.72 },
  { "name": "Michael Dumortier", "cost": 16.30 },
  { "name": "Alexander Ryckeboer", "cost": 12.55 },
  { "name": "Steven Robijns", "cost": 11.10 },
  { "name": "Tom Mennes", "cost": 6.47 },
  { "name": "Bert Vervaele", "cost": 6.31 },
  { "name": "Michael Branders", "cost": 5.09 },
  { "name": "Pierre Bossé", "cost": 4.34 },
  { "name": "Willem Meylemans", "cost": 2.73 },
  { "name": "Tyara Schetgens", "cost": 0.32 }
]
